src/Dataset.py
src/Label.py
src/Project.py
src/__init__.py
src/connection.py
smartlabel-0.0.1.dist-info/LICENSE
smartlabel-0.0.1.dist-info/METADATA
smartlabel-0.0.1.dist-info/WHEEL
smartlabel-0.0.1.dist-info/top_level.txt
smartlabel-0.0.1.dist-info/RECORD
