Metadata-Version: 2.1
Name: smartlabel
Version: 0.0.1
Summary: A command line interface to smartlabel.digital
Home-page: https://smartlabel.digital/cli
Author: Talha Abdullah
Author-email: zain@smartlabel.digital
License: UNKNOWN
Platform: UNKNOWN
Classifier: Programming Language :: Python :: 3
Classifier: License :: OSI Approved :: MIT License
Classifier: Operating System :: OS Independent
Requires-Python: >=3.6
